bin/ast_to_js
json_codegen/__init__.py
json_codegen/astlib/__init__.py
json_codegen/astlib/javascript.py
json_codegen/astlib/python.py
json_codegen/cli.py
json_codegen/core.py
json_codegen/generators/__init__.py
json_codegen/generators/flow.py
json_codegen/generators/javascript_flow.py
json_codegen/generators/python3.py
json_codegen/generators/python3_marshmallow/__init__.py
json_codegen/generators/python3_marshmallow/generator.py
json_codegen/generators/python3_marshmallow/object_generator.py
json_codegen/generators/python3_marshmallow/utils.py
json_codegen/js_utils.py
json_codegen/types.py
json_codegen-0.6.0.dist-info/METADATA
json_codegen-0.6.0.dist-info/entry_points.txt
json_codegen-0.6.0.dist-info/WHEEL
json_codegen-0.6.0.dist-info/LICENSE
json_codegen-0.6.0.dist-info/RECORD
