Metadata-Version: 2.1
Name: json-codegen
Version: 0.6.0
Summary: Generate code from JSON schema files.
License: MIT
Keywords: python,javascript,json-schema,codegen
Author: Daniele Esposti
Author-email: daniele.esposti@gmail.com
Requires-Python: >=3.7,<3.8
Classifier: License :: OSI Approved :: MIT License
Classifier: Programming Language :: Python :: 3
Classifier: Programming Language :: Python :: 3.7
Requires-Dist: astor (>=0.7.1)
